peewee_migrate/__init__.py
peewee_migrate/__main__.py
peewee_migrate/auto.py
peewee_migrate/cli.py
peewee_migrate/logs.py
peewee_migrate/migrator.py
peewee_migrate/models.py
peewee_migrate/py.typed
peewee_migrate/router.py
peewee_migrate/template.py
peewee_migrate/types.py
peewee_migrate/utils.py
peewee_migrate-1.14.2.dist-info/METADATA
peewee_migrate-1.14.2.dist-info/WHEEL
peewee_migrate-1.14.2.dist-info/entry_points.txt
peewee_migrate-1.14.2.dist-info/licenses/LICENSE
peewee_migrate-1.14.2.dist-info/RECORD
