Metadata-Version: 2.4
Name: peewee-migrate
Version: 1.14.2
Summary: Support for migrations in Peewee ORM
License: MIT
License-File: LICENSE
Keywords: peewee,migrations,orm
Author: Kirill Klenov
Author-email: horneds@gmail.com
Requires-Python: >=3.10,<4.0
Classifier: Development Status :: 5 - Production/Stable
Classifier: Intended Audience :: Developers
Classifier: License :: OSI Approved :: MIT License
Classifier: Programming Language :: Python
Classifier: Programming Language :: Python :: 3
Classifier: Programming Language :: Python :: 3.10
Classifier: Programming Language :: Python :: 3.11
Classifier: Programming Language :: Python :: 3.12
Classifier: Programming Language :: Python :: 3.13
Classifier: Programming Language :: Python :: 3.14
Classifier: Topic :: Software Development :: Libraries :: Python Modules
Classifier: Topic :: Utilities
Requires-Dist: click
Requires-Dist: peewee (>=3,<4)
Project-URL: Homepage, https://github.com/klen/peewee_migrate
Project-URL: Repository, https://github.com/klen/peewee_migrate
